{
  "cordova-plugin-whitelist": {
    "source": {
      "type": "registry",
      "id": "cordova-plugin-whitelist@1"
    },
    "is_top_level": true,
    "variables": {}
  },
  "cordova-plugin-device": {
    "source": {
      "type": "registry",
      "id": "cordova-plugin-device"
    },
    "is_top_level": true,
    "variables": {}
  },
  "cordova-plugin-facebook4": {
    "source": {
      "type": "registry",
      "id": "cordova-plugin-facebook4@^1.8.0"
    },
    "is_top_level": true,
    "variables": {
      "APP_ID": "461226704259165",
      "APP_NAME": "MuscularStrength"
    }
  },
  "cordova-plugin-inappbrowser": {
    "source": {
      "type": "registry",
      "id": "cordova-plugin-inappbrowser@^1.7.2"
    },
    "is_top_level": true,
    "variables": {}
  },
  "cordova-plugin-splashscreen": {
    "source": {
      "type": "registry",
      "id": "cordova-plugin-splashscreen@^4.0.3"
    },
    "is_top_level": true,
    "variables": {}
  },
  "cordova-plugin-x-socialsharing": {
    "source": {
      "type": "registry",
      "id": "git+https://github.com/EddyVerbruggen/SocialSharing-PhoneGap-Plugin.git"
    },
    "is_top_level": true,
    "variables": {}
  },
  "es6-promise-plugin": {
    "source": {
      "type": "registry",
      "id": "es6-promise-plugin@^4.1.0"
    },
    "is_top_level": false,
    "variables": {}
  },
  "cordova-plugin-statusbar": {
    "source": {
      "type": "registry",
      "id": "cordova-plugin-statusbar@2.4.2"
    },
    "is_top_level": true,
    "variables": {}
  },
  "cordova-plugin-firebase": {
    "source": {
      "type": "registry",
      "id": "cordova-plugin-firebase"
    },
    "is_top_level": true,
    "variables": {}
  }
}